.gitignore
LICENSE.txt
MANIFEST.in
README.md
SECURITY.md
setup.py
Richdata/__init__.py
Richdata/abcdatabase.py
Richdata/bigquery.py
Richdata/google.py
Richdata/helpers.py
Richdata/postgres.py
Richdata/sqlserver.py
Richdata.egg-info/PKG-INFO
Richdata.egg-info/SOURCES.txt
Richdata.egg-info/dependency_links.txt
Richdata.egg-info/requires.txt
Richdata.egg-info/top_level.txt