Metadata-Version: 2.1
Name: Richdata
Version: 0.5.1
Summary: Rich data and Data Engineering
Home-page: https://github.com/rimedinaz/richdata
Author: Richard Medina
Author-email: rimedinaz@gmail.com
License: Apache License 2.0
Platform: UNKNOWN
Classifier: Programming Language :: Python :: 3
Classifier: License :: OSI Approved :: Apache Software License
Classifier: Operating System :: OS Independent
Requires-Python: >=3.3
Provides-Extra: sqlserver
Provides-Extra: postgres
Provides-Extra: bigquery
Provides-Extra: all
License-File: LICENSE.txt
